[
    {
      "title": "Telewizor LG LED 50UK6950 ",
      "price": 2299.99,
      "diagonal": "50 ",
      "isProductAvailable": true,
      "productUrl": "/telewizory/telewizor-lg-led-50uk6950,id-1100821"
    },
    {
      "title": "Telewizor LG LED 55UK6470PLC ",
      "price": 2299.99,
      "diagonal": "55 ",
      "isProductAvailable": true,
      "productUrl": "/telewizory/telewizor-lg-led-55uk6470plc,id-1100825"
    },
    {
      "title": "Telewizor LG OLED55B8PLA ",
      "price": 5895,
      "diagonal": "55 ",
      "isProductAvailable": true,
      "productUrl": "/telewizory/telewizor-lg-oled55b8pla,id-1100759"
    },
    {
      "title": "Telewizor LG LED 50UK6470 ",
      "price": 1699,
      "diagonal": "50 ",
      "isProductAvailable": true,
      "productUrl": "/telewizory/telewizor-lg-led-50uk6470,id-1100831"
    },
    {
      "title": "Telewizor LG LED 55SK8000PLB ",
      "price": 3199,
      "diagonal": "55 ",
      "isProductAvailable": true,
      "productUrl": "/telewizory/telewizor-lg-led-55sk8000plb,id-1100779"
    },
    {
      "title": "Telewizor LG LED 49SK8000PLB ",
      "price": 2999.99,
      "diagonal": "49 ",
      "isProductAvailable": true,
      "productUrl": "/telewizory/telewizor-lg-led-49sk8000plb,id-1100783"
    },
    {
      "title": "Telewizor LG LED 43UK6470 ",
      "price": 1699.99,
      "diagonal": "43 ",
      "isProductAvailable": true,
      "productUrl": "/telewizory/telewizor-lg-led-43uk6470,id-1100861"
    },
    {
      "title": "Telewizor LG LED 55UK6950PLB ",
      "price": 2664,
      "diagonal": "55 ",
      "isProductAvailable": true,
      "productUrl": "/telewizory/telewizor-lg-led-55uk6950plb,id-1100811"
    },
    {
      "title": "Telewizor LG LED 43UK6950 ",
      "price": 1999.99,
      "diagonal": "43 ",
      "isProductAvailable": true,
      "productUrl": "/telewizory/telewizor-lg-led-43uk6950,id-1100843"
    },
    {
      "title": "Telewizor LG LED 55SK9500PLA ",
      "price": 6199,
      "diagonal": "55 ",
      "isProductAvailable": true,
      "productUrl": "/telewizory/telewizor-lg-led-55sk9500pla,id-1100767"
    },
    {
      "title": "Telewizor LG LED 55SK8500 ",
      "price": 4999,
      "diagonal": "55 ",
      "isProductAvailable": true,
      "productUrl": "/telewizory/telewizor-lg-led-55sk8500,id-1100775"
    },
    {
      "title": "Telewizor LG LED 55UK6750PLD ",
      "price": 2801.33,
      "diagonal": "55 ",
      "isProductAvailable": true,
      "productUrl": "/telewizory/telewizor-lg-led-55uk6750pld,id-1100813"
    },
    {
      "title": "Telewizor LG OLED55E7N ",
      "price": 9429.99,
      "diagonal": "55 ",
      "isProductAvailable": true,
      "productUrl": "/telewizory/telewizor-lg-oled55e7n,id-823480"
    },
    {
      "title": "Telewizor LG OLED55E8PLA ",
      "price": 8995,
      "diagonal": "55 ",
      "isProductAvailable": true,
      "productUrl": "/telewizory/telewizor-lg-oled55e8pla,id-1100755"
    },
    {
      "title": "Telewizor LG OLED55C8PLA ",
      "price": 6999,
      "diagonal": "55 ",
      "isProductAvailable": true,
      "productUrl": "/telewizory/telewizor-lg-oled55c8pla,id-1100757"
    },
    {
      "title": "Telewizor LG LED 49UK6300MLB ",
      "price": 2183.23,
      "diagonal": "49 ",
      "isProductAvailable": true,
      "productUrl": "/telewizory/telewizor-lg-led-49uk6300mlb,id-1100841"
    },
    {
      "title": "Telewizor LG LED 49SK8100PLA ",
      "price": 3707.48,
      "diagonal": "49 ",
      "isProductAvailable": true,
      "productUrl": "/telewizory/telewizor-lg-led-49sk8100pla,id-1100795"
    },
    {
      "title": "Telewizor LG LED 43UK6300PLB ",
      "price": null,
      "diagonal": "43 ",
      "isProductAvailable": true,
      "productUrl": "/telewizory/telewizor-lg-led-43uk6300plb,id-1100849"
    },
    {
      "title": "Telewizor LG LED 55UJ620V ",
      "price": 0,
      "diagonal": "55 ",
      "isProductAvailable": false,
      "productUrl": "/telewizory/telewizor-lg-led-55uj620v,id-988252"
    },
    {
      "title": "Telewizor LG LED 43UK6750PLD ",
      "price": 0,
      "diagonal": "43 ",
      "isProductAvailable": false,
      "productUrl": "/telewizory/telewizor-lg-led-43uk6750pld,id-1100845"
    },
    {
      "title": "Telewizor LG LED 49UJ701V ",
      "price": 0,
      "diagonal": "49 ",
      "isProductAvailable": false,
      "productUrl": "/telewizory/telewizor-lg-led-49uj701v,id-827606"
    },
    {
      "title": "Telewizor LG LED 49UK6470PLC ",
      "price": 0,
      "diagonal": "49 ",
      "isProductAvailable": false,
      "productUrl": "/telewizory/telewizor-lg-led-49uk6470plc,id-1100837"
    },
    {
      "title": "Telewizor LG LED 43UJ670V ",
      "price": 0,
      "diagonal": "43 ",
      "isProductAvailable": false,
      "productUrl": "/telewizory/telewizor-lg-led-43uj670v,id-827618"
    },
    {
      "title": "Telewizor LG LED 43UJ620V ",
      "price": 0,
      "diagonal": "43 ",
      "isProductAvailable": false,
      "productUrl": "/telewizory/telewizor-lg-led-43uj620v,id-988248"
    },
    {
      "title": "Telewizor LG LED 49UJ620V ",
      "price": 0,
      "diagonal": "49 ",
      "isProductAvailable": false,
      "productUrl": "/telewizory/telewizor-lg-led-49uj620v,id-988250"
    },
    {
      "title": "Telewizor LG LED 49UJ635V ",
      "price": 0,
      "diagonal": "49 ",
      "isProductAvailable": false,
      "productUrl": "/telewizory/telewizor-lg-led-49uj635v,id-827660"
    },
    {
      "title": "Telewizor LG LED 43UJ701V ",
      "price": 0,
      "diagonal": "43 ",
      "isProductAvailable": false,
      "productUrl": "/telewizory/telewizor-lg-led-43uj701v,id-827604"
    },
    {
      "title": "Telewizor LG LED 49UK6400PLF ",
      "price": 0,
      "diagonal": "49 ",
      "isProductAvailable": false,
      "productUrl": "/telewizory/telewizor-lg-led-49uk6400plf,id-1100839"
    },
    {
      "title": "Telewizor LG LED 55UJ635V ",
      "price": 0,
      "diagonal": "55 ",
      "isProductAvailable": false,
      "productUrl": "/telewizory/telewizor-lg-led-55uj635v,id-827658"
    },
    {
      "title": "Telewizor LG LED 50UK6300MLB ",
      "price": 0,
      "diagonal": "50 ",
      "isProductAvailable": false,
      "productUrl": "/telewizory/telewizor-lg-led-50uk6300mlb,id-1100833"
    },
    {
      "title": "Telewizor LG LED 43UK6500MLA ",
      "price": 0,
      "diagonal": "43 ",
      "isProductAvailable": false,
      "productUrl": "/telewizory/telewizor-lg-led-43uk6500mla,id-1100847"
    },
    {
      "title": "Telewizor LG LED 55UJ701V ",
      "price": 0,
      "diagonal": "55 ",
      "isProductAvailable": false,
      "productUrl": "/telewizory/telewizor-lg-led-55uj701v,id-827652"
    },
    {
      "title": "Telewizor LG LED 55SK8100PLA ",
      "price": 0,
      "diagonal": "55 ",
      "isProductAvailable": false,
      "productUrl": "/telewizory/telewizor-lg-led-55sk8100pla,id-1100777"
    },
    {
      "title": "Telewizor LG LED 49UK7550 ",
      "price": 0,
      "diagonal": "49 ",
      "isProductAvailable": false,
      "productUrl": "/telewizory/telewizor-lg-led-49uk7550,id-1100835"
    },
    {
      "title": "Telewizor LG LED 43UJ635V ",
      "price": 0,
      "diagonal": "43 ",
      "isProductAvailable": false,
      "productUrl": "/telewizory/telewizor-lg-led-43uj635v,id-827662"
    },
    {
      "title": "Telewizor LG LED 50UK6750PLD ",
      "price": 0,
      "diagonal": "50 ",
      "isProductAvailable": false,
      "productUrl": "/telewizory/telewizor-lg-led-50uk6750pld,id-1100829"
    },
    {
      "title": "Telewizor LG LED 49SK8500 ",
      "price": 0,
      "diagonal": "49 ",
      "isProductAvailable": true,
      "productUrl": "/telewizory/telewizor-lg-led-49sk8500,id-1100793"
    },
    {
      "title": "Telewizor LG LED 55UK6300 ",
      "price": 0,
      "diagonal": "55 ",
      "isProductAvailable": true,
      "productUrl": "/telewizory/telewizor-lg-led-55uk6300,id-1100827"
    }
  ]